Metadata-Version: 2.4
Name: llm-fragments-reddit
Version: 0.1.1
Summary: A plugin for llm to load Reddit threads as fragments
Author: banteg
License-Expression: MIT
Requires-Python: >=3.12
Requires-Dist: llm>=0.26
Requires-Dist: requests>=2.32.3
